{
  "timestamp": "2026-06-13 15:08:20",
  "phase": "Phase 3: CSV Data Integration Design",
  "status": "COMPLETED",
  "documents_created": [
    "docs/PHASE3_CSV_INTEGRATION.md",
    "docs/LISTING_DATA_MODEL.md",
    "examples/listing_input_sample.csv",
    "examples/research_to_listing_mapping.md",
    "src/csv_integration/__init__.py",
    "src/csv_integration/listing_record.py",
    "src/csv_integration/csv_mapper.py",
    "src/csv_integration/csv_validator.py"
  ],
  "key_design_decisions": {
    "csv_integration_strategy": "Two-stage transformation (Research CSV → Listing CSV)",
    "sku_strategy": "Auto-generation (MARGIN-YYYYMMDD-NNNN format)",
    "image_mapping": "SKU-based directory resolution (data/images/{SKU}/)",
    "research_listing_separation": "Distinct responsibilities, maintained traceability via candidate_id"
  },
  "data_layers": {
    "layer_1": "Validated & Normalized Record (CSV validation + type checking)",
    "layer_2": "Listing Preparation Record (SKU assignment + image resolution)",
    "layer_3": "Listing-Ready Record (final validation + audit trail)"
  },
  "validation_levels": {
    "hard_error": "Unresolvable issues - row skipped",
    "soft_warning": "Missing optional data - processing continues with notification",
    "pending_review": "Data can be completed by user - marked for review",
    "skip": "Row explicitly skipped (research_status != confirmed)"
  },
  "next_phase": "Phase 4: eBay Payload Builder Implementation",
  "next_phase_scope": [
    "eBay category ID mapping implementation",
    "eBay title generation logic",
    "eBay description template application",
    "Price & Quantity decision rules",
    "Payload serialization to eBay API format"
  ]
}